{
  "date": "2026-07-09",
  "jcd": "15",
  "venue": "丸亀",
  "title": "丸亀初日展望、香川はA1重成ら3人",
  "body": "中讃テレビ杯が丸亀で開幕する。地元・香川から名を連ねたのは3人。A1は重成一人ただ一枚で、あとはB1の長谷川親王とB2の下田哲也が続く。重成は全国勝率5.97に対し当地勝率6.70と、丸亀の水面で数字を上げるタイプ。当地2連率は46.53%だ。乗る36号機は今節2連率35.9%で、節平均33.6%を上回る一台。決まり手は逃げ型で、直近1着36本の内訳は逃げ16・まくり差し6。差し率19.4%がまくり率5.6%を上回り、内から差す形が持ち味になる。場の実数も押さえておきたい。丸亀は過去1年でイン先頭決着が55.2%（2314レース）、年間万舟率は17.2%、荒れ率は31.9%。半分強がインで決まる、締まった数字が並ぶ。初日の丸亀は、A1・重成の一枚を地元の柱に据える。その当地勝率6.70と、イン先頭55.2%という場の数字を並べて、香川三枚の一節が幕を開ける。",
  "styleType": "展望型",
  "killerElement": "初日、地元香川はA1重成一人ら3人、イン先頭年間55.2%の場の実数を下敷きに開幕",
  "glossaryTerms": [
    "当地勝率",
    "2連率",
    "差し",
    "まくり",
    "イン",
    "万舟"
  ],
  "racersMentioned": [
    {
      "name": "重成一人",
      "toban": "3908"
    }
  ]
}