{
 "date": "2026-07-14",
 "jcd": "01",
 "venue": "桐生",
 "title": "桐生開幕、イン半分の荒れ水面",
 "body": "第４８回デイリースポーツ杯が、桐生で開幕する。当場は年間万舟率が19.6%（2365レース）と全国でも高い部類、イン先頭決着48.5%、荒れ率35.3%。インが半分に届かず、外の仕掛けが通りやすい荒れ含みの水面だ。地元・群馬はA2の土屋千明が全国勝率6.42・当地2連率44.26%、A1の坂本雄紀が当地2連率46.62%と続く。土屋の24号機は今節2連率36.31%で節平均36.5%とほぼ並ぶ。イン半分の荒れ水面に、地元勢がどう乗るか。場の実数と当地の数字を下敷きに、初日の桐生が始まる。",
 "styleType": "展望型",
 "killerElement": "初日、年間万舟率19.6%の荒れ水面と地元群馬の土屋・坂本",
 "glossaryTerms": [
  "万舟",
  "イン先頭決着率",
  "荒れ率",
  "当地勝率",
  "2連率",
  "節平均",
  "逃げ"
 ],
 "racersMentioned": [
  {
   "name": "土屋千明",
   "toban": "4225"
  },
  {
   "name": "坂本雄紀",
   "toban": "5150"
  }
 ]
}