{"開催日":"20251028","生成時刻":"2026-07-06T04:48:25+09:00","閾値":{"堅め":0.09,"波乱":-0.09},"予測":[{"場名":"江戸川","場コード":"03","レース":"1R","判定":"混戦","主役艇":1,"スコア":0.042},{"場名":"江戸川","場コード":"03","レース":"2R","判定":"混戦","主役艇":1,"スコア":0.038},{"場名":"江戸川","場コード":"03","レース":"3R","判定":"堅め","主役艇":1,"スコア":0.264},{"場名":"江戸川","場コード":"03","レース":"4R","判定":"堅め","主役艇":1,"スコア":0.177},{"場名":"江戸川","場コード":"03","レース":"5R","判定":"堅め","主役艇":1,"スコア":0.124},{"場名":"江戸川","場コード":"03","レース":"6R","判定":"堅め","主役艇":1,"スコア":0.341},{"場名":"江戸川","場コード":"03","レース":"7R","判定":"混戦","主役艇":1,"スコア":0.051},{"場名":"江戸川","場コード":"03","レース":"8R","判定":"波乱","主役艇":4,"スコア":-0.113},{"場名":"江戸川","場コード":"03","レース":"9R","判定":"堅め","主役艇":1,"スコア":0.291},{"場名":"江戸川","場コード":"03","レース":"10R","判定":"堅め","主役艇":1,"スコア":0.266},{"場名":"江戸川","場コード":"03","レース":"11R","判定":"堅め","主役艇":1,"スコア":0.182},{"場名":"江戸川","場コード":"03","レース":"12R","判定":"堅め","主役艇":1,"スコア":0.152},{"場名":"浜名湖","場コード":"06","レース":"1R","判定":"堅め","主役艇":1,"スコア":0.118},{"場名":"浜名湖","場コード":"06","レース":"2R","判定":"波乱","主役艇":4,"スコア":-0.104},{"場名":"浜名湖","場コード":"06","レース":"3R","判定":"波乱","主役艇":4,"スコア":-0.18},{"場名":"浜名湖","場コード":"06","レース":"4R","判定":"混戦","主役艇":1,"スコア":0.001},{"場名":"浜名湖","場コード":"06","レース":"5R","判定":"堅め","主役艇":1,"スコア":0.269},{"場名":"浜名湖","場コード":"06","レース":"6R","判定":"混戦","主役艇":1,"スコア":-0.037},{"場名":"浜名湖","場コード":"06","レース":"7R","判定":"堅め","主役艇":1,"スコア":0.329},{"場名":"浜名湖","場コード":"06","レース":"8R","判定":"混戦","主役艇":4,"スコア":-0.037},{"場名":"浜名湖","場コード":"06","レース":"9R","判定":"混戦","主役艇":4,"スコア":-0.048},{"場名":"浜名湖","場コード":"06","レース":"10R","判定":"混戦","主役艇":4,"スコア":0.002},{"場名":"浜名湖","場コード":"06","レース":"11R","判定":"混戦","主役艇":1,"スコア":0.053},{"場名":"浜名湖","場コード":"06","レース":"12R","判定":"混戦","主役艇":4,"スコア":0.04},{"場名":"常滑","場コード":"08","レース":"1R","判定":"堅め","主役艇":1,"スコア":0.222},{"場名":"常滑","場コード":"08","レース":"2R","判定":"混戦","主役艇":4,"スコア":-0.073},{"場名":"常滑","場コード":"08","レース":"3R","判定":"波乱","主役艇":4,"スコア":-0.145},{"場名":"常滑","場コード":"08","レース":"4R","判定":"混戦","主役艇":4,"スコア":-0.008},{"場名":"常滑","場コード":"08","レース":"5R","判定":"堅め","主役艇":1,"スコア":0.306},{"場名":"常滑","場コード":"08","レース":"6R","判定":"堅め","主役艇":1,"スコア":0.428},{"場名":"常滑","場コード":"08","レース":"7R","判定":"堅め","主役艇":1,"スコア":0.192},{"場名":"常滑","場コード":"08","レース":"8R","判定":"堅め","主役艇":1,"スコア":0.298},{"場名":"常滑","場コード":"08","レース":"9R","判定":"堅め","主役艇":1,"スコア":0.17},{"場名":"常滑","場コード":"08","レース":"10R","判定":"混戦","主役艇":4,"スコア":0.016},{"場名":"常滑","場コード":"08","レース":"11R","判定":"堅め","主役艇":1,"スコア":0.234},{"場名":"常滑","場コード":"08","レース":"12R","判定":"混戦","主役艇":1,"スコア":-0.042},{"場名":"びわこ","場コード":"11","レース":"1R","判定":"堅め","主役艇":1,"スコア":0.306},{"場名":"びわこ","場コード":"11","レース":"2R","判定":"堅め","主役艇":1,"スコア":0.206},{"場名":"びわこ","場コード":"11","レース":"3R","判定":"堅め","主役艇":1,"スコア":0.318},{"場名":"びわこ","場コード":"11","レース":"4R","判定":"混戦","主役艇":4,"スコア":-0.04},{"場名":"びわこ","場コード":"11","レース":"5R","判定":"混戦","主役艇":1,"スコア":0.023},{"場名":"びわこ","場コード":"11","レース":"6R","判定":"混戦","主役艇":1,"スコア":0.053},{"場名":"びわこ","場コード":"11","レース":"7R","判定":"混戦","主役艇":1,"スコア":0.072},{"場名":"びわこ","場コード":"11","レース":"8R","判定":"堅め","主役艇":1,"スコア":0.126},{"場名":"びわこ","場コード":"11","レース":"9R","判定":"混戦","主役艇":1,"スコア":0.065},{"場名":"びわこ","場コード":"11","レース":"10R","判定":"堅め","主役艇":1,"スコア":0.109},{"場名":"びわこ","場コード":"11","レース":"11R","判定":"混戦","主役艇":4,"スコア":0.003},{"場名":"びわこ","場コード":"11","レース":"12R","判定":"堅め","主役艇":1,"スコア":0.142},{"場名":"住之江","場コード":"12","レース":"1R","判定":"堅め","主役艇":1,"スコア":0.163},{"場名":"住之江","場コード":"12","レース":"2R","判定":"堅め","主役艇":1,"スコア":0.207},{"場名":"住之江","場コード":"12","レース":"3R","判定":"堅め","主役艇":1,"スコア":0.249},{"場名":"住之江","場コード":"12","レース":"4R","判定":"堅め","主役艇":1,"スコア":0.139},{"場名":"住之江","場コード":"12","レース":"5R","判定":"堅め","主役艇":1,"スコア":0.32},{"場名":"住之江","場コード":"12","レース":"6R","判定":"堅め","主役艇":1,"スコア":0.351},{"場名":"住之江","場コード":"12","レース":"7R","判定":"堅め","主役艇":1,"スコア":0.12},{"場名":"住之江","場コード":"12","レース":"8R","判定":"堅め","主役艇":1,"スコア":0.274},{"場名":"住之江","場コード":"12","レース":"9R","判定":"波乱","主役艇":4,"スコア":-0.152},{"場名":"住之江","場コード":"12","レース":"10R","判定":"混戦","主役艇":1,"スコア":0.043},{"場名":"住之江","場コード":"12","レース":"11R","判定":"堅め","主役艇":1,"スコア":0.122},{"場名":"住之江","場コード":"12","レース":"12R","判定":"混戦","主役艇":1,"スコア":-0.029},{"場名":"鳴門","場コード":"14","レース":"1R","判定":"堅め","主役艇":1,"スコア":0.172},{"場名":"鳴門","場コード":"14","レース":"2R","判定":"波乱","主役艇":4,"スコア":-0.204},{"場名":"鳴門","場コード":"14","レース":"3R","判定":"堅め","主役艇":1,"スコア":0.146},{"場名":"鳴門","場コード":"14","レース":"4R","判定":"堅め","主役艇":1,"スコア":0.204},{"場名":"鳴門","場コード":"14","レース":"5R","判定":"波乱","主役艇":4,"スコア":-0.287},{"場名":"鳴門","場コード":"14","レース":"6R","判定":"堅め","主役艇":1,"スコア":0.202},{"場名":"鳴門","場コード":"14","レース":"7R","判定":"波乱","主役艇":4,"スコア":-0.115},{"場名":"鳴門","場コード":"14","レース":"8R","判定":"波乱","主役艇":4,"スコア":-0.177},{"場名":"鳴門","場コード":"14","レース":"9R","判定":"混戦","主役艇":1,"スコア":-0.071},{"場名":"鳴門","場コード":"14","レース":"10R","判定":"混戦","主役艇":4,"スコア":-0.024},{"場名":"鳴門","場コード":"14","レース":"11R","判定":"混戦","主役艇":1,"スコア":0.035},{"場名":"鳴門","場コード":"14","レース":"12R","判定":"堅め","主役艇":1,"スコア":0.232},{"場名":"宮島","場コード":"17","レース":"1R","判定":"堅め","主役艇":1,"スコア":0.126},{"場名":"宮島","場コード":"17","レース":"2R","判定":"波乱","主役艇":4,"スコア":-0.2},{"場名":"宮島","場コード":"17","レース":"3R","判定":"波乱","主役艇":4,"スコア":-0.14},{"場名":"宮島","場コード":"17","レース":"4R","判定":"混戦","主役艇":1,"スコア":0.047},{"場名":"宮島","場コード":"17","レース":"5R","判定":"堅め","主役艇":1,"スコア":0.093},{"場名":"宮島","場コード":"17","レース":"6R","判定":"堅め","主役艇":1,"スコア":0.13},{"場名":"宮島","場コード":"17","レース":"7R","判定":"堅め","主役艇":1,"スコア":0.344},{"場名":"宮島","場コード":"17","レース":"8R","判定":"混戦","主役艇":1,"スコア":-0.022},{"場名":"宮島","場コード":"17","レース":"9R","判定":"混戦","主役艇":1,"スコア":0.046},{"場名":"宮島","場コード":"17","レース":"10R","判定":"混戦","主役艇":1,"スコア":-0.065},{"場名":"宮島","場コード":"17","レース":"11R","判定":"堅め","主役艇":1,"スコア":0.151},{"場名":"宮島","場コード":"17","レース":"12R","判定":"混戦","主役艇":1,"スコア":0.004},{"場名":"下関","場コード":"19","レース":"1R","判定":"混戦","主役艇":1,"スコア":0.004},{"場名":"下関","場コード":"19","レース":"2R","判定":"混戦","主役艇":1,"スコア":-0.003},{"場名":"下関","場コード":"19","レース":"3R","判定":"混戦","主役艇":4,"スコア":-0.037},{"場名":"下関","場コード":"19","レース":"4R","判定":"波乱","主役艇":4,"スコア":-0.115},{"場名":"下関","場コード":"19","レース":"5R","判定":"混戦","主役艇":1,"スコア":0.081},{"場名":"下関","場コード":"19","レース":"6R","判定":"混戦","主役艇":4,"スコア":-0.037},{"場名":"下関","場コード":"19","レース":"7R","判定":"混戦","主役艇":4,"スコア":-0.035},{"場名":"下関","場コード":"19","レース":"8R","判定":"混戦","主役艇":1,"スコア":0.04},{"場名":"下関","場コード":"19","レース":"9R","判定":"堅め","主役艇":1,"スコア":0.101},{"場名":"下関","場コード":"19","レース":"10R","判定":"堅め","主役艇":1,"スコア":0.115},{"場名":"下関","場コード":"19","レース":"11R","判定":"混戦","主役艇":1,"スコア":-0.004},{"場名":"下関","場コード":"19","レース":"12R","判定":"混戦","主役艇":1,"スコア":0.002},{"場名":"芦屋","場コード":"21","レース":"1R","判定":"堅め","主役艇":1,"スコア":0.156},{"場名":"芦屋","場コード":"21","レース":"2R","判定":"混戦","主役艇":1,"スコア":-0.08},{"場名":"芦屋","場コード":"21","レース":"3R","判定":"混戦","主役艇":1,"スコア":0.068},{"場名":"芦屋","場コード":"21","レース":"4R","判定":"堅め","主役艇":1,"スコア":0.197},{"場名":"芦屋","場コード":"21","レース":"5R","判定":"混戦","主役艇":4,"スコア":0.02},{"場名":"芦屋","場コード":"21","レース":"6R","判定":"混戦","主役艇":1,"スコア":-0.017},{"場名":"芦屋","場コード":"21","レース":"7R","判定":"波乱","主役艇":4,"スコア":-0.13},{"場名":"芦屋","場コード":"21","レース":"8R","判定":"波乱","主役艇":4,"スコア":-0.13},{"場名":"芦屋","場コード":"21","レース":"9R","判定":"堅め","主役艇":1,"スコア":0.198},{"場名":"芦屋","場コード":"21","レース":"10R","判定":"波乱","主役艇":4,"スコア":-0.127},{"場名":"芦屋","場コード":"21","レース":"11R","判定":"波乱","主役艇":4,"スコア":-0.102},{"場名":"芦屋","場コード":"21","レース":"12R","判定":"混戦","主役艇":4,"スコア":-0.07},{"場名":"福岡","場コード":"22","レース":"1R","判定":"堅め","主役艇":1,"スコア":0.286},{"場名":"福岡","場コード":"22","レース":"2R","判定":"波乱","主役艇":4,"スコア":-0.206},{"場名":"福岡","場コード":"22","レース":"3R","判定":"混戦","主役艇":4,"スコア":-0.05},{"場名":"福岡","場コード":"22","レース":"4R","判定":"混戦","主役艇":1,"スコア":-0.084},{"場名":"福岡","場コード":"22","レース":"5R","判定":"波乱","主役艇":4,"スコア":-0.276},{"場名":"福岡","場コード":"22","レース":"6R","判定":"混戦","主役艇":1,"スコア":0.03},{"場名":"福岡","場コード":"22","レース":"7R","判定":"波乱","主役艇":4,"スコア":-0.105},{"場名":"福岡","場コード":"22","レース":"8R","判定":"堅め","主役艇":1,"スコア":0.207},{"場名":"福岡","場コード":"22","レース":"9R","判定":"堅め","主役艇":1,"スコア":0.096},{"場名":"福岡","場コード":"22","レース":"10R","判定":"混戦","主役艇":1,"スコア":0.013},{"場名":"福岡","場コード":"22","レース":"11R","判定":"堅め","主役艇":1,"スコア":0.178},{"場名":"福岡","場コード":"22","レース":"12R","判定":"混戦","主役艇":1,"スコア":-0.031},{"場名":"大村","場コード":"24","レース":"1R","判定":"堅め","主役艇":1,"スコア":0.127},{"場名":"大村","場コード":"24","レース":"2R","判定":"堅め","主役艇":1,"スコア":0.119},{"場名":"大村","場コード":"24","レース":"3R","判定":"混戦","主役艇":4,"スコア":-0.035},{"場名":"大村","場コード":"24","レース":"4R","判定":"波乱","主役艇":4,"スコア":-0.105},{"場名":"大村","場コード":"24","レース":"5R","判定":"波乱","主役艇":4,"スコア":-0.245},{"場名":"大村","場コード":"24","レース":"6R","判定":"波乱","主役艇":4,"スコア":-0.333},{"場名":"大村","場コード":"24","レース":"7R","判定":"堅め","主役艇":1,"スコア":0.178},{"場名":"大村","場コード":"24","レース":"8R","判定":"混戦","主役艇":1,"スコア":-0.002},{"場名":"大村","場コード":"24","レース":"9R","判定":"堅め","主役艇":1,"スコア":0.105},{"場名":"大村","場コード":"24","レース":"10R","判定":"堅め","主役艇":1,"スコア":0.215},{"場名":"大村","場コード":"24","レース":"11R","判定":"堅め","主役艇":1,"スコア":0.196},{"場名":"大村","場コード":"24","レース":"12R","判定":"堅め","主役艇":1,"スコア":0.213}]},"波及ID":"S5","締めID":"C4"},{"場名":"鳴門","場コード":"14","レース":"11R","判定":"混戦","主役艇":1,"スコア":0.035,"対抗艇":3,"死角艇":2,"見出しID":"M6","死角ID":"D2","波及ID":"S5","締めID":"C5"},{"場名":"鳴門","場コード":"14","レース":"12R","判定":"堅め","主役艇":1,"スコア":0.232,"対抗艇":6,"死角艇":3,"見出しID":"M6","死角ID":"D2","波及ID":"S5","締めID":"C6"},{"場名":"宮島","場コード":"17","レース":"1R","判定":"堅め","主役艇":1,"スコア":0.126,"対抗艇":6,"死角艇":4,"見出しID":"K3","死角ID":"D1","波及ID":"S2","締めID":"C2"},{"場名":"宮島","場コード":"17","レース":"2R","判定":"波乱","主役艇":4,"スコア":-0.2,"対抗艇":3,"死角艇":4,"見出しID":"H3","死角ID":"D6","波及ID":"S5","締めID":"C3"},{"場名":"宮島","場コード":"17","レース":"3R","判定":"波乱","主役艇":4,"スコア":-0.14,"対抗艇":null,"死角艇":2,"見出しID":"M6","死角ID":"D2","波及ID":"S5","締めID":"C7"},{"場名":"宮島","場コード":"17","レース":"4R","判定":"混戦","主役艇":1,"スコア":0.047,"対抗艇":6,"死角艇":6,"見出しID":"M2","死角ID":"D1","波及ID":"S5","締めID":"C5"},{"場名":"宮島","場コード":"17","レース":"5R","判定":"堅め","主役艇":1,"スコア":0.093,"対抗艇":6,"死角艇":6,"見出しID":"M3","死角ID":"D1","波及ID":"S5","締めID":"C6"},{"場名":"宮島","場コード":"17","レース":"6R","判定":"堅め","主役艇":1,"スコア":0.13,"対抗艇":5,"死角艇":null,"見出しID":"M6","死角ID":"D12","波及ID":"S5","締めID":"C6"},{"場名":"宮島","場コード":"17","レース":"7R","判定":"堅め","主役艇":1,"スコア":0.344,"対抗艇":3,"死角艇":6,"見出しID":"M6","死角ID":"D1","波及ID":"S5","締めID":"C6"},{"場名":"宮島","場コード":"17","レース":"8R","判定":"混戦","主役艇":1,"スコア":-0.022,"対抗艇":3,"死角艇":4,"見出しID":"M3","死角ID":"D1","波及ID":"S5","締めID":"C5"},{"場名":"宮島","場コード":"17","レース":"9R","判定":"混戦","主役艇":1,"スコア":0.046,"対抗艇":6,"死角艇":2,"見出しID":"M3","死角ID":"D2","波及ID":"S5","締めID":"C5"},{"場名":"宮島","場コード":"17","レース":"10R","判定":"混戦","主役艇":1,"スコア":-0.065,"対抗艇":6,"死角艇":2,"見出しID":"M3","死角ID":"D2","波及ID":"S5","締めID":"C5"},{"場名":"宮島","場コード":"17","レース":"11R","判定":"堅め","主役艇":1,"スコア":0.151,"対抗艇":4,"死角艇":2,"見出しID":"K3","死角ID":"D2","波及ID":"S2","締めID":"C2"},{"場名":"宮島","場コード":"17","レース":"12R","判定":"混戦","主役艇":1,"スコア":0.004,"対抗艇":6,"死角艇":4,"見出しID":"K4","死角ID":"D1","波及ID":"S2","締めID":"C5"},{"場名":"下関","場コード":"19","レース":"1R","判定":"混戦","主役艇":1,"スコア":0.004,"対抗艇":6,"死角艇":6,"見出しID":"M6","死角ID":"D1","波及ID":"S5","締めID":"C5"},{"場名":"下関","場コード":"19","レース":"2R","判定":"混戦","主役艇":1,"スコア":-0.003,"対抗艇":5,"死角艇":4,"見出しID":"K4","死角ID":"D1","波及ID":"S1","締めID":"C5"},{"場名":"下関","場コード":"19","レース":"3R","判定":"混戦","主役艇":4,"スコア":-0.037,"対抗艇":5,"死角艇":null,"見出しID":"M6","死角ID":"D12","波及ID":"S5","締めID":"C4"},{"場名":"下関","場コード":"19","レース":"4R","判定":"波乱","主役艇":4,"スコア":-0.115,"対抗艇":3,"死角艇":4,"見出しID":"K4","死角ID":"D1","波及ID":"S1","締めID":"C7"},{"場名":"下関","場コード":"19","レース":"5R","判定":"混戦","主役艇":1,"スコア":0.081,"対抗艇":6,"死角艇":4,"見出しID":"M6","死角ID":"D1","波及ID":"S5","締めID":"C5"},{"場名":"下関","場コード":"19","レース":"6R","判定":"混戦","主役艇":4,"スコア":-0.037,"対抗艇":3,"死角艇":6,"見出しID":"M6","死角ID":"D1","波及ID":"S5","締めID":"C4"},{"場名":"下関","場コード":"19","レース":"7R","判定":"混戦","主役艇":4,"スコア":-0.035,"対抗艇":6,"死角艇":4,"見出しID":"K4","死角ID":"D1","波及ID":"S1","締めID":"C4"},{"場名":"下関","場コード":"19","レース":"8R","判定":"混戦","主役艇":1,"スコア":0.04,"対抗艇":6,"死角艇":4,"見出しID":"K4","死角ID":"D1","波及ID":"S1","締めID":"C5"},{"場名":"下関","場コード":"19","レース":"9R","判定":"堅め","主役艇":1,"スコア":0.101,"対抗艇":5,"死角艇":6,"見出しID":"M6","死角ID":"D1","波及ID":"S5","締めID":"C6"},{"場名":"下関","場コード":"19","レース":"10R","判定":"堅め","主役艇":1,"スコア":0.115,"対抗艇":6,"死角艇":2,"見出しID":"K2","死角ID":"D2","波及ID":"S1","締めID":"C2"},{"場名":"下関","場コード":"19","レース":"11R","判定":"混戦","主役艇":1,"スコア":-0.004,"対抗艇":6,"死角艇":3,"見出しID":"M6","死角ID":"D2","波及ID":"S5","締めID":"C5"},{"場名":"下関","場コード":"19","レース":"12R","判定":"混戦","主役艇":1,"スコア":0.002,"対抗艇":6,"死角艇":6,"見出しID":"K4","死角ID":"D1","波及ID":"S1","締めID":"C5"},{"場名":"芦屋","場コード":"21","レース":"1R","判定":"堅め","主役艇":1,"スコア":0.156,"対抗艇":null,"死角艇":null,"見出しID":"M7","死角ID":"D13","波及ID":"S2","締めID":"C6"},{"場名":"芦屋","場コード":"21","レース":"2R","判定":"混戦","主役艇":1,"スコア":-0.08,"対抗艇":null,"死角艇":2,"見出しID":"K4","死角ID":"D2","波及ID":"S1","締めID":"C5"},{"場名":"芦屋","場コード":"21","レース":"3R","判定":"混戦","主役艇":1,"スコア":0.068,"対抗艇":4,"死角艇":5,"見出しID":"K4","死角ID":"D1","波及ID":"S1","締めID":"C5"},{"場名":"芦屋","場コード":"21","レース":"4R","判定":"堅め","主役艇":1,"スコア":0.197,"対抗艇":4,"死角艇":4,"見出しID":"K2","死角ID":"D1","波及ID":"S1","締めID":"C2"},{"場名":"芦屋","場コード":"21","レース":"5R","判定":"混戦","主役艇":4,"スコア":0.02,"対抗艇":3,"死角艇":4,"見出しID":"M6","死角ID":"D1","波及ID":"S5","締めID":"C4"},{"場名":"芦屋","場コード":"21","レース":"6R","判定":"混戦","主役艇":1,"スコア":-0.017,"対抗艇":5,"死角艇":5,"見出しID":"M3","死角ID":"D1","波及ID":"S5","締めID":"C5"},{"場名":"芦屋","場コード":"21","レース":"7R","判定":"波乱","主役艇":4,"スコア":-0.13,"対抗艇":null,"死角艇":3,"見出しID":"M4","死角ID":"D4","波及ID":"S7","締めID":"C3"},{"場名":"芦屋","場コード":"21","レース":"8R","判定":"波乱","主役艇":4,"スコア":-0.13,"対抗艇":3,"死角艇":6,"見出しID":"H3","死角ID":"D1","波及ID":"S5","締めID":"C3"},{"場名":"芦屋","場コード":"21","レース":"9R","判定":"堅め","主役艇":1,"スコア":0.198,"対抗艇":5,"死角艇":4,"見出しID":"K2","死角ID":"D1","波及ID":"S1","締めID":"C2"},{"場名":"芦屋","場コード":"21","レース":"10R","判定":"波乱","主役艇":4,"スコア":-0.127,"対抗艇":5,"死角艇":4,"見出しID":"H3","死角ID":"D1","波及ID":"S5","締めID":"C3"},{"場名":"芦屋","場コード":"21","レース":"11R","判定":"波乱","主役艇":4,"スコア":-0.102,"対抗艇":5,"死角艇":4,"見出しID":"K4","死角ID":"D1","波及ID":"S1","締めID":"C7"},{"場名":"芦屋","場コード":"21","レース":"12R","判定":"混戦","主役艇":4,"スコア":-0.07,"対抗艇":6,"死角艇":null,"見出しID":"M6","死角ID":"D12","波及ID":"S5","締めID":"C4"},{"場名":"福岡","場コード":"22","レース":"1R","判定":"堅め","主役艇":1,"スコア":0.286,"対抗艇":null,"死角艇":1,"見出しID":"K3","死角ID":"D3","波及ID":"S2","締めID":"C2"},{"場名":"福岡","場コード":"22","レース":"2R","判定":"波乱","主役艇":4,"スコア":-0.206,"対抗艇":6,"死角艇":4,"見出しID":"H3","死角ID":"D1","波及ID":"S5","締めID":"C3"},{"場名":"福岡","場コード":"22","レース":"3R","判定":"混戦","主役艇":4,"スコア":-0.05,"対抗艇":3,"死角艇":6,"見出しID":"M3","死角ID":"D1","波及ID":"S5","締めID":"C4"},{"場名":"福岡","場コード":"22","レース":"4R","判定":"混戦","主役艇":1,"スコア":-0.084,"対抗艇":null,"死角艇":4,"見出しID":"M3","死角ID":"D1","波及ID":"S5","締めID":"C5"},{"場名":"福岡","場コード":"22","レース":"5R","判定":"波乱","主役艇":4,"スコア":-0.276,"対抗艇":3,"死角艇":1,"見出しID":"H3","死角ID":"D10","波及ID":"S5","締めID":"C3"},{"場名":"福岡","場コード":"22","レース":"6R","判定":"混戦","主役艇":1,"スコア":0.03,"対抗艇":3,"死角艇":6,"見出しID":"M2","死角ID":"D1","波及ID":"S5","締めID":"C5"},{"場名":"福岡","場コード":"22","レース":"7R","判定":"波乱","主役艇":4,"スコア":-0.105,"対抗艇":3,"死角艇":3,"見出しID":"M6","死角ID":"D2","波及ID":"S5","締めID":"C7"},{"場名":"福岡","場コード":"22","レース":"8R","判定":"堅め","主役艇":1,"スコア":0.207,"対抗艇":3,"死角艇":2,"見出しID":"M6","死角ID":"D2","波及ID":"S5","締めID":"C6"},{"場名":"福岡","場コード":"22","レース":"9R","判定":"堅め","主役艇":1,"スコア":0.096,"対抗艇":null,"死角艇":3,"見出しID":"M3","死角ID":"D2","波及ID":"S5","締めID":"C6"},{"場名":"福岡","場コード":"22","レース":"10R","判定":"混戦","主役艇":1,"スコア":0.013,"対抗艇":5,"死角艇":null,"見出しID":"M6","死角ID":"D12","波及ID":"S5","締めID":"C5"},{"場名":"福岡","場コード":"22","レース":"11R","判定":"堅め","主役艇":1,"スコア":0.178,"対抗艇":null,"死角艇":4,"見出しID":"K3","死角ID":"D1","波及ID":"S2","締めID":"C2"},{"場名":"福岡","場コード":"22","レース":"12R","判定":"混戦","主役艇":1,"スコア":-0.031,"対抗艇":6,"死角艇":4,"見出しID":"K4","死角ID":"D1","波及ID":"S2","締めID":"C5"},{"場名":"大村","場コード":"24","レース":"1R","判定":"堅め","主役艇":1,"スコア":0.127,"対抗艇":6,"死角艇":5,"見出しID":"M3","死角ID":"D1","波及ID":"S5","締めID":"C6"},{"場名":"大村","場コード":"24","レース":"2R","判定":"堅め","主役艇":1,"スコア":0.119,"対抗艇":5,"死角艇":3,"見出しID":"M6","死角ID":"D2","波及ID":"S5","締めID":"C6"},{"場名":"大村","場コード":"24","レース":"3R","判定":"混戦","主役艇":4,"スコア":-0.035,"対抗艇":5,"死角艇":5,"見出しID":"M3","死角ID":"D1","波及ID":"S5","締めID":"C4"},{"場名":"大村","場コード":"24","レース":"4R","判定":"波乱","主役艇":4,"スコア":-0.105,"対抗艇":5,"死角艇":4,"見出しID":"H3","死角ID":"D1","波及ID":"S5","締めID":"C3"},{"場名":"大村","場コード":"24","レース":"5R","判定":"波乱","主役艇":4,"スコア":-0.245,"対抗艇":3,"死角艇":5,"見出しID":"H3","死角ID":"D1","波及ID":"S5","締めID":"C3"},{"場名":"大村","場コード":"24","レース":"6R","判定":"波乱","主役艇":4,"スコア":-0.333,"対抗艇":6,"死角艇":2,"見出しID":"H3","死角ID":"D2","波及ID":"S5","締めID":"C3"},{"場名":"大村","場コード":"24","レース":"7R","判定":"堅め","主役艇":1,"スコア":0.178,"対抗艇":4,"死角艇":4,"見出しID":"K2","死角ID":"D1","波及ID":"S1","締めID":"C2"},{"場名":"大村","場コード":"24","レース":"8R","判定":"混戦","主役艇":1,"スコア":-0.002,"対抗艇":3,"死角艇":3,"見出しID":"M3","死角ID":"D2","波及ID":"S5","締めID":"C5"},{"場名":"大村","場コード":"24","レース":"9R","判定":"堅め","主役艇":1,"スコア":0.105,"対抗艇":4,"死角艇":1,"見出しID":"K2","死角ID":"D3","波及ID":"S1","締めID":"C2"},{"場名":"大村","場コード":"24","レース":"10R","判定":"堅め","主役艇":1,"スコア":0.215,"対抗艇":5,"死角艇":4,"見出しID":"M6","死角ID":"D1","波及ID":"S5","締めID":"C6"},{"場名":"大村","場コード":"24","レース":"11R","判定":"堅め","主役艇":1,"スコア":0.196,"対抗艇":5,"死角艇":4,"見出しID":"M6","死角ID":"D1","波及ID":"S5","締めID":"C6"},{"場名":"大村","場コード":"24","レース":"12R","判定":"堅め","主役艇":1,"スコア":0.213,"対抗艇":5,"死角艇":5,"見出しID":"M6","死角ID":"D1","波及ID":"S5","締めID":"C6"}]}