{"開催日":"20260521","生成時刻":"2026-07-07T10:34:56+09:00","閾値":{"堅め":0.04,"波乱":-0.09},"予測":[{"場名":"桐生","場コード":"01","レース":"1R","判定":"堅め","主役艇":1,"スコア":0.052,"対抗艇":6,"死角艇":1,"見出しID":"M1","死角ID":"D7","波及ID":"S4","締めID":"C6"},{"場名":"桐生","場コード":"01","レース":"2R","判定":"波乱","主役艇":4,"スコア":-0.056,"対抗艇":6,"死角艇":1,"見出しID":"H3","死角ID":"D9","波及ID":"S5","締めID":"C3"},{"場名":"桐生","場コード":"01","レース":"3R","判定":"波乱","主役艇":4,"スコア":-0.153,"対抗艇":6,"死角艇":1,"見出しID":"H3","死角ID":"D10","波及ID":"S5","締めID":"C3"},{"場名":"桐生","場コード":"01","レース":"4R","判定":"波乱","主役艇":4,"スコア":-0.043,"対抗艇":6,"死角艇":1,"見出しID":"H3","死角ID":"D8","波及ID":"S5","締めID":"C3"},{"場名":"桐生","場コード":"01","レース":"5R","判定":"波乱","主役艇":4,"スコア":-0.266,"対抗艇":6,"死角艇":1,"見出しID":"H3","死角ID":"D8","波及ID":"S5","締めID":"C3"},{"場名":"桐生","場コード":"01","レース":"6R","判定":"堅め","主役艇":1,"スコア":0.249,"対抗艇":5,"死角艇":1,"見出しID":"K3","死角ID":"D3","波及ID":"S2","締めID":"C2"},{"場名":"桐生","場コード":"01","レース":"7R","判定":"堅め","主役艇":1,"スコア":0.099,"対抗艇":5,"死角艇":1,"見出しID":"M3","死角ID":"D8","波及ID":"S5","締めID":"C6"},{"場名":"桐生","場コード":"01","レース":"8R","判定":"堅め","主役艇":1,"スコア":0.1,"対抗艇":5,"死角艇":4,"見出しID":"M6","死角ID":"D12","波及ID":"S5","締めID":"C6"},{"場名":"桐生","場コード":"01","レース":"9R","判定":"波乱","主役艇":4,"スコア":-0.114,"対抗艇":6,"死角艇":1,"見出しID":"H3","死角ID":"D9","波及ID":"S5","締めID":"C3"},{"場名":"桐生","場コード":"01","レース":"10R","判定":"波乱","主役艇":4,"スコア":-0.11,"対抗艇":null,"死角艇":4,"見出しID":"M6","死角ID":"D12","波及ID":"S5","締めID":"C7"},{"場名":"桐生","場コード":"01","レース":"11R","判定":"堅め","主役艇":1,"スコア":0.068,"対抗艇":6,"死角艇":4,"見出しID":"M6","死角ID":"D12","波及ID":"S5","締めID":"C6"},{"場名":"桐生","場コード":"01","レース":"12R","判定":"堅め","主役艇":1,"スコア":0.152,"対抗艇":3,"死角艇":4,"見出しID":"M6","死角ID":"D12","波及ID":"S5","締めID":"C6"},{"場名":"多摩川","場コード":"05","レース":"1R","判定":"混戦","主役艇":1,"スコア":0.005,"対抗艇":6,"死角艇":1,"見出しID":"M3","死角ID":"D8","波及ID":"S5","締めID":"C5"},{"場名":"多摩川","場コード":"05","レース":"2R","判定":"混戦","主役艇":1,"スコア":-0.034,"対抗艇":3,"死角艇":1,"見出しID":"M3","死角ID":"D10","波及ID":"S5","締めID":"C5"},{"場名":"多摩川","場コード":"05","レース":"3R","判定":"波乱","主役艇":4,"スコア":-0.061,"対抗艇":3,"死角艇":3,"見出しID":"H3","死角ID":"D4","波及ID":"S5","締めID":"C3"},{"場名":"多摩川","場コード":"05","レース":"4R","判定":"堅め","主役艇":1,"スコア":0.122,"対抗艇":5,"死角艇":3,"見出しID":"M3","死角ID":"D2","波及ID":"S5","締めID":"C6"},{"場名":"多摩川","場コード":"05","レース":"5R","判定":"波乱","主役艇":4,"スコア":-0.228,"対抗艇":3,"死角艇":4,"見出しID":"H3","死角ID":"D6","波及ID":"S5","締めID":"C3"},{"場名":"多摩川","場コード":"05","レース":"6R","判定":"堅め","主役艇":1,"スコア":0.176,"対抗艇":null,"死角艇":1,"見出しID":"M3","死角ID":"D10","波及ID":"S5","締めID":"C6"},{"場名":"多摩川","場コード":"05","レース":"7R","判定":"堅め","主役艇":1,"スコア":0.113,"対抗艇":5,"死角艇":1,"見出しID":"K3","死角ID":"D3","波及ID":"S2","締めID":"C2"},{"場名":"多摩川","場コード":"05","レース":"8R","判定":"混戦","主役艇":1,"スコア":-0.003,"対抗艇":3,"死角艇":3,"見出しID":"M1","死角ID":"D4","波及ID":"S4","締めID":"C5"},{"場名":"多摩川","場コード":"05","レース":"9R","判定":"堅め","主役艇":1,"スコア":0.284,"対抗艇":null,"死角艇":1,"見出しID":"K3","死角ID":"D3","波及ID":"S2","締めID":"C2"},{"場名":"多摩川","場コード":"05","レース":"10R","判定":"堅め","主役艇":1,"スコア":0.106,"対抗艇":6,"死角艇":4,"見出しID":"M2","死角ID":"D6","波及ID":"S5","締めID":"C6"},{"場名":"多摩川","場コード":"05","レース":"11R","判定":"堅め","主役艇":1,"スコア":0.155,"対抗艇":6,"死角艇":3,"見出しID":"M2","死角ID":"D4","波及ID":"S5","締めID":"C6"},{"場名":"多摩川","場コード":"05","レース":"12R","判定":"堅め","主役艇":1,"スコア":0.036,"対抗艇":3,"死角艇":4,"見出しID":"M6","死角ID":"D12","波及ID":"S5","締めID":"C6"},{"場名":"常滑","場コード":"08","レース":"1R","判定":"堅め","主役艇":1,"スコア":0.292,"対抗艇":4,"死角艇":1,"見出しID":"K3","死角ID":"D3","波及ID":"S2","締めID":"C2"},{"場名":"常滑","場コード":"08","レース":"2R","判定":"波乱","主役艇":4,"スコア":-0.193,"対抗艇":5,"死角艇":1,"見出しID":"H3","死角ID":"D9","波及ID":"S5","締めID":"C3"},{"場名":"常滑","場コード":"08","レース":"3R","判定":"堅め","主役艇":1,"スコア":0.064,"対抗艇":3,"死角艇":3,"見出しID":"M3","死角ID":"D2","波及ID":"S5","締めID":"C6"},{"場名":"常滑","場コード":"08","レース":"4R","判定":"波乱","主役艇":4,"スコア":-0.246,"対抗艇":6,"死角艇":1,"見出しID":"H3","死角ID":"D10","波及ID":"S5","締めID":"C3"},{"場名":"常滑","場コード":"08","レース":"5R","判定":"堅め","主役艇":1,"スコア":0.099,"対抗艇":6,"死角艇":4,"見出しID":"M6","死角ID":"D12","波及ID":"S5","締めID":"C6"},{"場名":"常滑","場コード":"08","レース":"6R","判定":"波乱","主役艇":4,"スコア":-0.09,"対抗艇":5,"死角艇":1,"見出しID":"H3","死角ID":"D3","波及ID":"S2","締めID":"C7"},{"場名":"常滑","場コード":"08","レース":"7R","判定":"堅め","主役艇":1,"スコア":0.188,"対抗艇":6,"死角艇":1,"見出しID":"K3","死角ID":"D3","波及ID":"S2","締めID":"C2"},{"場名":"常滑","場コード":"08","レース":"8R","判定":"波乱","主役艇":4,"スコア":-0.29,"対抗艇":5,"死角艇":1,"見出しID":"H3","死角ID":"D10","波及ID":"S5","締めID":"C3"},{"場名":"常滑","場コード":"08","レース":"9R","判定":"混戦","主役艇":1,"スコア":-0.019,"対抗艇":null,"死角艇":1,"見出しID":"M5","死角ID":"D8","波及ID":"S7","締めID":"C5"},{"場名":"常滑","場コード":"08","レース":"10R","判定":"波乱","主役艇":4,"スコア":-0.083,"対抗艇":6,"死角艇":1,"見出しID":"H3","死角ID":"D8","波及ID":"S5","締めID":"C3"},{"場名":"常滑","場コード":"08","レース":"11R","判定":"堅め","主役艇":1,"スコア":0.184,"対抗艇":5,"死角艇":4,"見出しID":"M6","死角ID":"D12","波及ID":"S4","締めID":"C6"},{"場名":"常滑","場コード":"08","レース":"12R","判定":"堅め","主役艇":1,"スコア":0.096,"対抗艇":6,"死角艇":1,"見出しID":"K3","死角ID":"D3","波及ID":"S2","締めID":"C2"},{"場名":"津","場コード":"09","レース":"1R","判定":"堅め","主役艇":1,"スコア":0.081,"対抗艇":5,"死角艇":4,"見出しID":"M6","死角ID":"D12","波及ID":"S4","締めID":"C6"},{"場名":"津","場コード":"09","レース":"2R","判定":"混戦","主役艇":1,"スコア":-0.03,"対抗艇":null,"死角艇":1,"見出しID":"M3","死角ID":"D9","波及ID":"S5","締めID":"C5"},{"場名":"津","場コード":"09","レース":"3R","判定":"混戦","主役艇":1,"スコア":-0.017,"対抗艇":6,"死角艇":1,"見出しID":"M3","死角ID":"D8","波及ID":"S5","締めID":"C5"},{"場名":"津","場コード":"09","レース":"4R","判定":"波乱","主役艇":4,"スコア":-0.05,"対抗艇":6,"死角艇":1,"見出しID":"H3","死角ID":"D10","波及ID":"S5","締めID":"C3"},{"場名":"津","場コード":"09","レース":"5R","判定":"堅め","主役艇":1,"スコア":0.231,"対抗艇":5,"死角艇":1,"見出しID":"K3","死角ID":"D3","波及ID":"S2","締めID":"C2"},{"場名":"津","場コード":"09","レース":"6R","判定":"波乱","主役艇":4,"スコア":-0.139,"対抗艇":6,"死角艇":1,"見出しID":"H3","死角ID":"D10","波及ID":"S5","締めID":"C3"},{"場名":"津","場コード":"09","レース":"7R","判定":"波乱","主役艇":4,"スコア":-0.083,"対抗艇":5,"死角艇":1,"見出しID":"H3","死角ID":"D9","波及ID":"S5","締めID":"C3"},{"場名":"津","場コード":"09","レース":"8R","判定":"波乱","主役艇":4,"スコア":-0.206,"対抗艇":6,"死角艇":1,"見出しID":"H3","死角ID":"D9","波及ID":"S5","締めID":"C3"},{"場名":"津","場コード":"09","レース":"9R","判定":"波乱","主役艇":4,"スコア":-0.143,"対抗艇":5,"死角艇":1,"見出しID":"H3","死角ID":"D9","波及ID":"S5","締めID":"C3"},{"場名":"津","場コード":"09","レース":"10R","判定":"波乱","主役艇":4,"スコア":-0.133,"対抗艇":6,"死角艇":4,"見出しID":"M6","死角ID":"D12","波及ID":"S5","締めID":"C7"},{"場名":"津","場コード":"09","レース":"11R","判定":"波乱","主役艇":4,"スコア":-0.069,"対抗艇":3,"死角艇":1,"見出しID":"H3","死角ID":"D8","波及ID":"S5","締めID":"C3"},{"場名":"津","場コード":"09","レース":"12R","判定":"堅め","主役艇":1,"スコア":0.107,"対抗艇":5,"死角艇":4,"見出しID":"M6","死角ID":"D12","波及ID":"S5","締めID":"C6"},{"場名":"びわこ","場コード":"11","レース":"1R","判定":"波乱","主役艇":4,"スコア":-0.087,"対抗艇":5,"死角艇":4,"見出しID":"M6","死角ID":"D12","波及ID":"S5","締めID":"C7"},{"場名":"びわこ","場コード":"11","レース":"2R","判定":"混戦","主役艇":1,"スコア":0.052,"対抗艇":5,"死角艇":3,"見出しID":"M3","死角ID":"D4","波及ID":"S5","締めID":"C5"},{"場名":"びわこ","場コード":"11","レース":"3R","判定":"波乱","主役艇":4,"スコア":-0.166,"対抗艇":5,"死角艇":4,"見出しID":"M6","死角ID":"D12","波及ID":"S5","締めID":"C7"},{"場名":"びわこ","場コード":"11","レース":"4R","判定":"波乱","主役艇":4,"スコア":-0.235,"対抗艇":6,"死角艇":1,"見出しID":"H3","死角ID":"D8","波及ID":"S5","締めID":"C3"},{"場名":"びわこ","場コード":"11","レース":"5R","判定":"堅め","主役艇":1,"スコア":0.128,"対抗艇":6,"死角艇":4,"見出しID":"M6","死角ID":"D12","波及ID":"S5","締めID":"C6"},{"場名":"びわこ","場コード":"11","レース":"6R","判定":"混戦","主役艇":1,"スコア":0.012,"対抗艇":4,"死角艇":1,"見出しID":"K4","死角ID":"D3","波及ID":"S2","締めID":"C5"},{"場名":"びわこ","場コード":"11","レース":"7R","判定":"堅め","主役艇":1,"スコア":0.132,"対抗艇":5,"死角艇":4,"見出しID":"M6","死角ID":"D12","波及ID":"S5","締めID":"C6"},{"場名":"びわこ","場コード":"11","レース":"8R","判定":"混戦","主役艇":1,"スコア":0.02,"対抗艇":6,"死角艇":4,"見出しID":"M6","死角ID":"D12","波及ID":"S5","締めID":"C5"},{"場名":"びわこ","場コード":"11","レース":"9R","判定":"堅め","主役艇":1,"スコア":0.158,"対抗艇":4,"死角艇":1,"見出しID":"K3","死角ID":"D3","波及ID":"S2","締めID":"C2"},{"場名":"びわこ","場コード":"11","レース":"10R","判定":"混戦","主役艇":1,"スコア":0.068,"対抗艇":4,"死角艇":4,"見出しID":"K4","死角ID":"D1","波及ID":"S2","締めID":"C5"},{"場名":"びわこ","場コード":"11","レース":"11R","判定":"混戦","主役艇":1,"スコア":0.016,"対抗艇":3,"死角艇":1,"見出しID":"K4","死角ID":"D3","波及ID":"S2","締めID":"C5"},{"場名":"びわこ","場コード":"11","レース":"12R","判定":"混戦","主役艇":1,"スコア":-0.018,"対抗艇":6,"死角艇":4,"見出しID":"M6","死角ID":"D12","波及ID":"S5","締めID":"C5"},{"場名":"鳴門","場コード":"14","レース":"1R","判定":"堅め","主役艇":1,"スコア":0.252,"対抗艇":6,"死角艇":4,"見出しID":"M6","死角ID":"D12","波及ID":"S4","締めID":"C6"},{"場名":"鳴門","場コード":"14","レース":"2R","判定":"波乱","主役艇":4,"スコア":-0.087,"対抗艇":5,"死角艇":1,"見出しID":"H3","死角ID":"D8","波及ID":"S5","締めID":"C3"},{"場名":"鳴門","場コード":"14","レース":"3R","判定":"堅め","主役艇":1,"スコア":0.269,"対抗艇":null,"死角艇":1,"見出しID":"K3","死角ID":"D3","波及ID":"S2","締めID":"C2"},{"場名":"鳴門","場コード":"14","レース":"4R","判定":"波乱","主役艇":4,"スコア":-0.103,"対抗艇":3,"死角艇":3,"見出しID":"M6","死角ID":"D4","波及ID":"S5","締めID":"C7"},{"場名":"鳴門","場コード":"14","レース":"5R","判定":"堅め","主役艇":1,"スコア":0.138,"対抗艇":3,"死角艇":3,"見出しID":"M3","死角ID":"D4","波及ID":"S5","締めID":"C6"},{"場名":"鳴門","場コード":"14","レース":"6R","判定":"混戦","主役艇":1,"スコア":0.038,"対抗艇":6,"死角艇":4,"見出しID":"M2","死角ID":"D6","波及ID":"S5","締めID":"C5"},{"場名":"鳴門","場コード":"14","レース":"7R","判定":"波乱","主役艇":4,"スコア":-0.125,"対抗艇":3,"死角艇":5,"見出しID":"H3","死角ID":"D6","波及ID":"S5","締めID":"C3"},{"場名":"鳴門","場コード":"14","レース":"8R","判定":"混戦","主役艇":1,"スコア":0.002,"対抗艇":6,"死角艇":1,"見出しID":"M3","死角ID":"D8","波及ID":"S5","締めID":"C5"},{"場名":"鳴門","場コード":"14","レース":"9R","判定":"堅め","主役艇":1,"スコア":0.275,"対抗艇":3,"死角艇":1,"見出しID":"K3","死角ID":"D3","波及ID":"S2","締めID":"C2"},{"場名":"鳴門","場コード":"14","レース":"10R","判定":"堅め","主役艇":1,"スコア":0.083,"対抗艇":6,"死角艇":1,"見出しID":"M3","死角ID":"D8","波及ID":"S5","締めID":"C6"},{"場名":"鳴門","場コード":"14","レース":"11R","判定":"混戦","主役艇":1,"スコア":0.009,"対抗艇":6,"死角艇":1,"見出しID":"M3","死角ID":"D9","波及ID":"S5","締めID":"C5"},{"場名":"鳴門","場コード":"14","レース":"12R","判定":"波乱","主役艇":4,"スコア":-0.043,"対抗艇":6,"死角艇":4,"見出しID":"M6","死角ID":"D12","波及ID":"S5","締めID":"C7"},{"場名":"丸亀","場コード":"15","レース":"1R","判定":"波乱","主役艇":4,"スコア":-0.212,"対抗艇":3,"死角艇":2,"見出しID":"H3","死角ID":"D2","波及ID":"S5","締めID":"C3"},{"場名":"丸亀","場コード":"15","レース":"2R","判定":"波乱","主役艇":4,"スコア":-0.119,"対抗艇":6,"死角艇":1,"見出しID":"H3","死角ID":"D9","波及ID":"S5","締めID":"C3"},{"場名":"丸亀","場コード":"15","レース":"3R","判定":"波乱","主役艇":4,"スコア":-0.067,"対抗艇":6,"死角艇":4,"見出しID":"M6","死角ID":"D12","波及ID":"S5","締めID":"C7"},{"場名":"丸亀","場コード":"15","レース":"4R","判定":"波乱","主役艇":4,"スコア":-0.076,"対抗艇":6,"死角艇":1,"見出しID":"H3","死角ID":"D8","波及ID":"S5","締めID":"C3"},{"場名":"丸亀","場コード":"15","レース":"5R","判定":"堅め","主役艇":1,"スコア":0.076,"対抗艇":3,"死角艇":1,"見出しID":"M3","死角ID":"D8","波及ID":"S5","締めID":"C6"},{"場名":"丸亀","場コード":"15","レース":"6R","判定":"混戦","主役艇":1,"スコア":0.005,"対抗艇":6,"死角艇":1,"見出しID":"M3","死角ID":"D9","波及ID":"S5","締めID":"C5"},{"場名":"丸亀","場コード":"15","レース":"7R","判定":"堅め","主役艇":1,"スコア":0.176,"対抗艇":6,"死角艇":4,"見出しID":"M6","死角ID":"D12","波及ID":"S5","締めID":"C6"},{"場名":"丸亀","場コード":"15","レース":"8R","判定":"波乱","主役艇":4,"スコア":-0.063,"対抗艇":5,"死角艇":4,"見出しID":"M6","死角ID":"D12","波及ID":"S5","締めID":"C7"},{"場名":"丸亀","場コード":"15","レース":"9R","判定":"波乱","主役艇":4,"スコア":-0.099,"対抗艇":6,"死角艇":4,"見出しID":"M6","死角ID":"D12","波及ID":"S5","締めID":"C7"},{"場名":"丸亀","場コード":"15","レース":"10R","判定":"堅め","主役艇":1,"スコア":0.126,"対抗艇":6,"死角艇":1,"見出しID":"M3","死角ID":"D8","波及ID":"S5","締めID":"C6"},{"場名":"丸亀","場コード":"15","レース":"11R","判定":"堅め","主役艇":1,"スコア":0.189,"対抗艇":5,"死角艇":1,"見出しID":"M3","死角ID":"D8","波及ID":"S5","締めID":"C6"},{"場名":"丸亀","場コード":"15","レース":"12R","判定":"混戦","主役艇":1,"スコア":0.023,"対抗艇":3,"死角艇":4,"見出しID":"M6","死角ID":"D12","波及ID":"S5","締めID":"C5"},{"場名":"児島","場コード":"16","レース":"1R","判定":"混戦","主役艇":1,"スコア":0.105,"対抗艇":null,"死角艇":1,"見出しID":"M5","死角ID":"D8","波及ID":"S7","締めID":"C5"},{"場名":"児島","場コード":"16","レース":"2R","判定":"混戦","主役艇":1,"スコア":0.03,"対抗艇":6,"死角艇":5,"見出しID":"M2","死角ID":"D6","波及ID":"S5","締めID":"C5"},{"場名":"児島","場コード":"16","レース":"3R","判定":"波乱","主役艇":4,"スコア":-0.235,"対抗艇":6,"死角艇":1,"見出しID":"H3","死角ID":"D10","波及ID":"S5","締めID":"C3"},{"場名":"児島","場コード":"16","レース":"4R","判定":"波乱","主役艇":4,"スコア":-0.288,"対抗艇":5,"死角艇":4,"見出しID":"H3","死角ID":"D1","波及ID":"S5","締めID":"C3"},{"場名":"児島","場コード":"16","レース":"5R","判定":"混戦","主役艇":1,"スコア":0.054,"対抗艇":3,"死角艇":3,"見出しID":"M3","死角ID":"D4","波及ID":"S5","締めID":"C5"},{"場名":"児島","場コード":"16","レース":"6R","判定":"混戦","主役艇":1,"スコア":0.042,"対抗艇":5,"死角艇":2,"見出しID":"M3","死角ID":"D2","波及ID":"S5","締めID":"C5"},{"場名":"児島","場コード":"16","レース":"7R","判定":"波乱","主役艇":4,"スコア":-0.204,"対抗艇":6,"死角艇":1,"見出しID":"H3","死角ID":"D10","波及ID":"S5","締めID":"C3"},{"場名":"児島","場コード":"16","レース":"8R","判定":"波乱","主役艇":4,"スコア":-0.073,"対抗艇":3,"死角艇":3,"見出しID":"H3","死角ID":"D4","波及ID":"S5","締めID":"C3"},{"場名":"児島","場コード":"16","レース":"9R","判定":"堅め","主役艇":1,"スコア":0.145,"対抗艇":null,"死角艇":6,"見出しID":"M6","死角ID":"D12","波及ID":"S5","締めID":"C6"},{"場名":"児島","場コード":"16","レース":"10R","判定":"混戦","主役艇":1,"スコア":0.024,"対抗艇":3,"死角艇":5,"見出しID":"M3","死角ID":"D1","波及ID":"S5","締めID":"C5"},{"場名":"児島","場コード":"16","レース":"11R","判定":"波乱","主役艇":4,"スコア":-0.06,"対抗艇":null,"死角艇":1,"見出しID":"H3","死角ID":"D3","波及ID":"S2","締めID":"C7"},{"場名":"児島","場コード":"16","レース":"12R","判定":"混戦","主役艇":1,"スコア":0.024,"対抗艇":5,"死角艇":1,"見出しID":"K4","死角ID":"D3","波及ID":"S2","締めID":"C5"},{"場名":"宮島","場コード":"17","レース":"1R","判定":"堅め","主役艇":1,"スコア":0.157,"対抗艇":5,"死角艇":4,"見出しID":"M6","死角ID":"D12","波及ID":"S5","締めID":"C6"},{"場名":"宮島","場コード":"17","レース":"2R","判定":"混戦","主役艇":1,"スコア":-0.001,"対抗艇":null,"死角艇":1,"見出しID":"M3","死角ID":"D8","波及ID":"S5","締めID":"C5"},{"場名":"宮島","場コード":"17","レース":"3R","判定":"波乱","主役艇":4,"スコア":-0.118,"対抗艇":6,"死角艇":1,"見出しID":"H3","死角ID":"D10","波及ID":"S5","締めID":"C3"},{"場名":"宮島","場コード":"17","レース":"4R","判定":"波乱","主役艇":4,"スコア":-0.065,"対抗艇":5,"死角艇":1,"見出しID":"H3","死角ID":"D9","波及ID":"S5","締めID":"C3"},{"場名":"宮島","場コード":"17","レース":"5R","判定":"堅め","主役艇":1,"スコア":0.247,"対抗艇":6,"死角艇":5,"見出しID":"M6","死角ID":"D12","波及ID":"S5","締めID":"C6"},{"場名":"宮島","場コード":"17","レース":"6R","判定":"混戦","主役艇":1,"スコア":0.07,"対抗艇":3,"死角艇":4,"見出しID":"M2","死角ID":"D6","波及ID":"S5","締めID":"C5"},{"場名":"宮島","場コード":"17","レース":"7R","判定":"堅め","主役艇":1,"スコア":0.163,"対抗艇":null,"死角艇":3,"見出しID":"M4","死角ID":"D4","波及ID":"S7","締めID":"C6"},{"場名":"宮島","場コード":"17","レース":"8R","判定":"堅め","主役艇":1,"スコア":0.148,"対抗艇":null,"死角艇":1,"見出しID":"K3","死角ID":"D3","波及ID":"S2","締めID":"C2"},{"場名":"宮島","場コード":"17","レース":"9R","判定":"堅め","主役艇":1,"スコア":0.121,"対抗艇":4,"死角艇":1,"見出しID":"K3","死角ID":"D3","波及ID":"S2","締めID":"C2"},{"場名":"宮島","場コード":"17","レース":"10R","判定":"波乱","主役艇":4,"スコア":-0.093,"対抗艇":3,"死角艇":1,"見出しID":"H3","死角ID":"D10","波及ID":"S5","締めID":"C3"},{"場名":"宮島","場コード":"17","レース":"11R","判定":"堅め","主役艇":1,"スコア":0.091,"対抗艇":5,"死角艇":4,"見出しID":"M6","死角ID":"D12","波及ID":"S5","締めID":"C6"},{"場名":"宮島","場コード":"17","レース":"12R","判定":"混戦","主役艇":1,"スコア":-0.007,"対抗艇":5,"死角艇":4,"見出しID":"M6","死角ID":"D12","波及ID":"S5","締めID":"C5"},{"場名":"徳山","場コード":"18","レース":"1R","判定":"堅め","主役艇":1,"スコア":0.219,"対抗艇":3,"死角艇":6,"見出しID":"M6","死角ID":"D12","波及ID":"S5","締めID":"C6"},{"場名":"徳山","場コード":"18","レース":"2R","判定":"堅め","主役艇":1,"スコア":0.223,"対抗艇":5,"死角艇":1,"見出しID":"K2","死角ID":"D3","波及ID":"S1","締めID":"C2"},{"場名":"徳山","場コード":"18","レース":"3R","判定":"混戦","主役艇":1,"スコア":0.032,"対抗艇":6,"死角艇":1,"見出しID":"K4","死角ID":"D3","波及ID":"S1","締めID":"C5"},{"場名":"徳山","場コード":"18","レース":"4R","判定":"堅め","主役艇":1,"スコア":0.312,"対抗艇":6,"死角艇":1,"見出しID":"K1","死角ID":"D3","波及ID":"S1","締めID":"C1"},{"場名":"徳山","場コード":"18","レース":"5R","判定":"波乱","主役艇":4,"スコア":-0.061,"対抗艇":null,"死角艇":1,"見出しID":"H3","死角ID":"D9","波及ID":"S5","締めID":"C3"},{"場名":"徳山","場コード":"18","レース":"6R","判定":"波乱","主役艇":4,"スコア":-0.095,"対抗艇":6,"死角艇":1,"見出しID":"H3","死角ID":"D10","波及ID":"S5","締めID":"C3"},{"場名":"徳山","場コード":"18","レース":"7R","判定":"混戦","主役艇":1,"スコア":0.008,"対抗艇":3,"死角艇":1,"見出しID":"M3","死角ID":"D8","波及ID":"S5","締めID":"C5"},{"場名":"徳山","場コード":"18","レース":"8R","判定":"波乱","主役艇":4,"スコア":-0.352,"対抗艇":3,"死角艇":3,"見出しID":"H3","死角ID":"D4","波及ID":"S5","締めID":"C3"},{"場名":"徳山","場コード":"18","レース":"9R","判定":"堅め","主役艇":1,"スコア":0.295,"対抗艇":3,"死角艇":1,"見出しID":"K2","死角ID":"D3","波及ID":"S1","締めID":"C2"},{"場名":"徳山","場コード":"18","レース":"10R","判定":"堅め","主役艇":1,"スコア":0.203,"対抗艇":6,"死角艇":5,"見出しID":"M6","死角ID":"D12","波及ID":"S5","締めID":"C6"},{"場名":"徳山","場コード":"18","レース":"11R","判定":"堅め","主役艇":1,"スコア":0.265,"対抗艇":5,"死角艇":1,"見出しID":"K2","死角ID":"D3","波及ID":"S1","締めID":"C2"},{"場名":"徳山","場コード":"18","レース":"12R","判定":"混戦","主役艇":1,"スコア":0.018,"対抗艇":3,"死角艇":4,"見出しID":"M6","死角ID":"D12","波及ID":"S4","締めID":"C5"},{"場名":"下関","場コード":"19","レース":"1R","判定":"堅め","主役艇":1,"スコア":0.069,"対抗艇":3,"死角艇":1,"見出しID":"M3","死角ID":"D9","波及ID":"S5","締めID":"C6"},{"場名":"下関","場コード":"19","レース":"2R","判定":"波乱","主役艇":4,"スコア":-0.184,"対抗艇":null,"死角艇":1,"見出しID":"H3","死角ID":"D8","波及ID":"S5","締めID":"C3"},{"場名":"下関","場コード":"19","レース":"3R","判定":"堅め","主役艇":1,"スコア":0.04,"対抗艇":3,"死角艇":5,"見出しID":"M6","死角ID":"D12","波及ID":"S5","締めID":"C6"},{"場名":"下関","場コード":"19","レース":"4R","判定":"波乱","主役艇":4,"スコア":-0.066,"対抗艇":3,"死角艇":1,"見出しID":"H3","死角ID":"D3","波及ID":"S1","締めID":"C7"},{"場名":"下関","場コード":"19","レース":"5R","判定":"堅め","主役艇":1,"スコア":0.078,"対抗艇":6,"死角艇":4,"見出しID":"M6","死角ID":"D12","波及ID":"S5","締めID":"C6"},{"場名":"下関","場コード":"19","レース":"6R","判定":"混戦","主役艇":1,"スコア":-0.023,"対抗艇":3,"死角艇":4,"見出しID":"M6","死角ID":"D12","波及ID":"S5","締めID":"C5"},{"場名":"下関","場コード":"19","レース":"7R","判定":"混戦","主役艇":1,"スコア":-0.002,"対抗艇":6,"死角艇":4,"見出しID":"M6","死角ID":"D12","波及ID":"S5","締めID":"C5"},{"場名":"下関","場コード":"19","レース":"8R","判定":"堅め","主役艇":1,"スコア":0.324,"対抗艇":null,"死角艇":1,"見出しID":"M7","死角ID":"D13","波及ID":"S2","締めID":"C6"},{"場名":"下関","場コード":"19","レース":"9R","判定":"堅め","主役艇":1,"スコア":0.131,"対抗艇":null,"死角艇":1,"見出しID":"M7","死角ID":"D13","波及ID":"S2","締めID":"C6"},{"場名":"下関","場コード":"19","レース":"10R","判定":"混戦","主役艇":1,"スコア":-0.045,"対抗艇":5,"死角艇":4,"見出しID":"M6","死角ID":"D12","波及ID":"S5","締めID":"C5"},{"場名":"下関","場コード":"19","レース":"11R","判定":"堅め","主役艇":1,"スコア":0.2,"対抗艇":6,"死角艇":5,"見出しID":"M6","死角ID":"D12","波及ID":"S5","締めID":"C6"},{"場名":"下関","場コード":"19","レース":"12R","判定":"堅め","主役艇":1,"スコア":0.134,"対抗艇":5,"死角艇":1,"見出しID":"K2","死角ID":"D3","波及ID":"S1","締めID":"C2"}]}