{
 "開催日": "20260618",
 "取得時刻": "2026-07-05T19:05:01",
 "レース数": 155,
 "結果": [
  {
   "場コード": "01",
   "レース": "1R",
   "着順": "2-5-3",
   "1着": 2,
   "2着": 5,
   "3着": 3,
   "三連単配当": 6150
  },
  {
   "場コード": "01",
   "レース": "2R",
   "着順": "1-4-6",
   "1着": 1,
   "2着": 4,
   "3着": 6,
   "三連単配当": 1690
  },
  {
   "場コード": "01",
   "レース": "3R",
   "着順": "1-3-4",
   "1着": 1,
   "2着": 3,
   "3着": 4,
   "三連単配当": 1250
  },
  {
   "場コード": "01",
   "レース": "4R",
   "着順": "5-2-4",
   "1着": 5,
   "2着": 2,
   "3着": 4,
   "三連単配当": 21370
  },
  {
   "場コード": "01",
   "レース": "5R",
   "着順": "1-5-4",
   "1着": 1,
   "2着": 5,
   "3着": 4,
   "三連単配当": 13500
  },
  {
   "場コード": "01",
   "レース": "6R",
   "着順": "6-2-3",
   "1着": 6,
   "2着": 2,
   "3着": 3,
   "三連単配当": 213090
  },
  {
   "場コード": "01",
   "レース": "7R",
   "着順": "1-5-6",
   "1着": 1,
   "2着": 5,
   "3着": 6,
   "三連単配当": 4710
  },
  {
   "場コード": "01",
   "レース": "8R",
   "着順": "1-4-3",
   "1着": 1,
   "2着": 4,
   "3着": 3,
   "三連単配当": 6760
  },
  {
   "場コード": "01",
   "レース": "9R",
   "着順": "1-3-2",
   "1着": 1,
   "2着": 3,
   "3着": 2,
   "三連単配当": 1300
  },
  {
   "場コード": "01",
   "レース": "10R",
   "着順": "1-3-4",
   "1着": 1,
   "2着": 3,
   "3着": 4,
   "三連単配当": 1070
  },
  {
   "場コード": "01",
   "レース": "11R",
   "着順": "1-2-5",
   "1着": 1,
   "2着": 2,
   "3着": 5,
   "三連単配当": 2660
  },
  {
   "場コード": "01",
   "レース": "12R",
   "着順": "1-2-4",
   "1着": 1,
   "2着": 2,
   "3着": 4,
   "三連単配当": 690
  },
  {
   "場コード": "02",
   "レース": "1R",
   "着順": "1-2-4",
   "1着": 1,
   "2着": 2,
   "3着": 4,
   "三連単配当": 2170
  },
  {
   "場コード": "02",
   "レース": "2R",
   "着順": "2-1-5",
   "1着": 2,
   "2着": 1,
   "3着": 5,
   "三連単配当": 2720
  },
  {
   "場コード": "02",
   "レース": "3R",
   "着順": "3-2-1",
   "1着": 3,
   "2着": 2,
   "3着": 1,
   "三連単配当": 3280
  },
  {
   "場コード": "02",
   "レース": "4R",
   "着順": "2-6-3",
   "1着": 2,
   "2着": 6,
   "3着": 3,
   "三連単配当": 3610
  },
  {
   "場コード": "02",
   "レース": "5R",
   "着順": "2-1-4",
   "1着": 2,
   "2着": 1,
   "3着": 4,
   "三連単配当": 1780
  },
  {
   "場コード": "02",
   "レース": "6R",
   "着順": "2-4-5",
   "1着": 2,
   "2着": 4,
   "3着": 5,
   "三連単配当": 2230
  },
  {
   "場コード": "02",
   "レース": "7R",
   "着順": "3-1-4",
   "1着": 3,
   "2着": 1,
   "3着": 4,
   "三連単配当": 4610
  },
  {
   "場コード": "02",
   "レース": "8R",
   "着順": "2-6-4",
   "1着": 2,
   "2着": 6,
   "3着": 4,
   "三連単配当": 3480
  },
  {
   "場コード": "02",
   "レース": "9R",
   "着順": "2-1-5",
   "1着": 2,
   "2着": 1,
   "3着": 5,
   "三連単配当": 2650
  },
  {
   "場コード": "02",
   "レース": "10R",
   "着順": "2-1-5",
   "1着": 2,
   "2着": 1,
   "3着": 5,
   "三連単配当": 6000
  },
  {
   "場コード": "02",
   "レース": "11R",
   "着順": "5-6-1",
   "1着": 5,
   "2着": 6,
   "3着": 1,
   "三連単配当": 100260
  },
  {
   "場コード": "02",
   "レース": "12R",
   "着順": "1-4-2",
   "1着": 1,
   "2着": 4,
   "3着": 2,
   "三連単配当": 2790
  },
  {
   "場コード": "04",
   "レース": "1R",
   "着順": "3-4-5",
   "1着": 3,
   "2着": 4,
   "3着": 5,
   "三連単配当": 4720
  },
  {
   "場コード": "04",
   "レース": "2R",
   "着順": "1-6-2",
   "1着": 1,
   "2着": 6,
   "3着": 2,
   "三連単配当": 2630
  },
  {
   "場コード": "04",
   "レース": "3R",
   "着順": "4-1-5",
   "1着": 4,
   "2着": 1,
   "3着": 5,
   "三連単配当": 1170
  },
  {
   "場コード": "04",
   "レース": "4R",
   "着順": "1-2-3",
   "1着": 1,
   "2着": 2,
   "3着": 3,
   "三連単配当": 980
  },
  {
   "場コード": "04",
   "レース": "5R",
   "着順": "2-1-3",
   "1着": 2,
   "2着": 1,
   "3着": 3,
   "三連単配当": 13230
  },
  {
   "場コード": "04",
   "レース": "6R",
   "着順": "2-3-4",
   "1着": 2,
   "2着": 3,
   "3着": 4,
   "三連単配当": 16930
  },
  {
   "場コード": "04",
   "レース": "7R",
   "着順": "3-6-2",
   "1着": 3,
   "2着": 6,
   "3着": 2,
   "三連単配当": 2260
  },
  {
   "場コード": "04",
   "レース": "8R",
   "着順": "3-2-4",
   "1着": 3,
   "2着": 2,
   "3着": 4,
   "三連単配当": 14510
  },
  {
   "場コード": "04",
   "レース": "9R",
   "着順": "1-3-4",
   "1着": 1,
   "2着": 3,
   "3着": 4,
   "三連単配当": 3030
  },
  {
   "場コード": "04",
   "レース": "10R",
   "着順": "2-6-1",
   "1着": 2,
   "2着": 6,
   "3着": 1,
   "三連単配当": 19680
  },
  {
   "場コード": "04",
   "レース": "11R",
   "着順": "1-5-3",
   "1着": 1,
   "2着": 5,
   "3着": 3,
   "三連単配当": 1840
  },
  {
   "場コード": "04",
   "レース": "12R",
   "着順": "2-1-5",
   "1着": 2,
   "2着": 1,
   "3着": 5,
   "三連単配当": 3710
  },
  {
   "場コード": "05",
   "レース": "1R",
   "着順": "1-4-3",
   "1着": 1,
   "2着": 4,
   "3着": 3,
   "三連単配当": 21800
  },
  {
   "場コード": "05",
   "レース": "2R",
   "着順": "1-2-5",
   "1着": 1,
   "2着": 2,
   "3着": 5,
   "三連単配当": 7220
  },
  {
   "場コード": "05",
   "レース": "3R",
   "着順": "4-6-5",
   "1着": 4,
   "2着": 6,
   "3着": 5,
   "三連単配当": 1370
  },
  {
   "場コード": "05",
   "レース": "4R",
   "着順": "1-6-4",
   "1着": 1,
   "2着": 6,
   "3着": 4,
   "三連単配当": 24500
  },
  {
   "場コード": "05",
   "レース": "5R",
   "着順": "3-2-1",
   "1着": 3,
   "2着": 2,
   "3着": 1,
   "三連単配当": 2970
  },
  {
   "場コード": "05",
   "レース": "6R",
   "着順": "4-5-1",
   "1着": 4,
   "2着": 5,
   "3着": 1,
   "三連単配当": 1350
  },
  {
   "場コード": "05",
   "レース": "7R",
   "着順": "1-3-4",
   "1着": 1,
   "2着": 3,
   "3着": 4,
   "三連単配当": 430
  },
  {
   "場コード": "05",
   "レース": "8R",
   "着順": "1-2-3",
   "1着": 1,
   "2着": 2,
   "3着": 3,
   "三連単配当": 1650
  },
  {
   "場コード": "05",
   "レース": "9R",
   "着順": "1-2-6",
   "1着": 1,
   "2着": 2,
   "3着": 6,
   "三連単配当": 850
  },
  {
   "場コード": "05",
   "レース": "10R",
   "着順": "1-4-2",
   "1着": 1,
   "2着": 4,
   "3着": 2,
   "三連単配当": 580
  },
  {
   "場コード": "05",
   "レース": "11R",
   "着順": "1-3-6",
   "1着": 1,
   "2着": 3,
   "3着": 6,
   "三連単配当": 540
  },
  {
   "場コード": "05",
   "レース": "12R",
   "着順": "1-5-4",
   "1着": 1,
   "2着": 5,
   "3着": 4,
   "三連単配当": 1040
  },
  {
   "場コード": "07",
   "レース": "2R",
   "着順": "5-2-6",
   "1着": 5,
   "2着": 2,
   "3着": 6,
   "三連単配当": 3800
  },
  {
   "場コード": "07",
   "レース": "3R",
   "着順": "2-5-1",
   "1着": 2,
   "2着": 5,
   "3着": 1,
   "三連単配当": 2160
  },
  {
   "場コード": "07",
   "レース": "4R",
   "着順": "6-4-3",
   "1着": 6,
   "2着": 4,
   "3着": 3,
   "三連単配当": 4390
  },
  {
   "場コード": "07",
   "レース": "5R",
   "着順": "3-4-1",
   "1着": 3,
   "2着": 4,
   "3着": 1,
   "三連単配当": 9960
  },
  {
   "場コード": "07",
   "レース": "6R",
   "着順": "1-3-4",
   "1着": 1,
   "2着": 3,
   "3着": 4,
   "三連単配当": 1890
  },
  {
   "場コード": "07",
   "レース": "7R",
   "着順": "1-3-5",
   "1着": 1,
   "2着": 3,
   "3着": 5,
   "三連単配当": 520
  },
  {
   "場コード": "07",
   "レース": "8R",
   "着順": "6-1-4",
   "1着": 6,
   "2着": 1,
   "3着": 4,
   "三連単配当": 3450
  },
  {
   "場コード": "07",
   "レース": "9R",
   "着順": "4-1-6",
   "1着": 4,
   "2着": 1,
   "3着": 6,
   "三連単配当": 1840
  },
  {
   "場コード": "07",
   "レース": "10R",
   "着順": "1-5-3",
   "1着": 1,
   "2着": 5,
   "3着": 3,
   "三連単配当": 5770
  },
  {
   "場コード": "07",
   "レース": "11R",
   "着順": "1-6-5",
   "1着": 1,
   "2着": 6,
   "3着": 5,
   "三連単配当": 5390
  },
  {
   "場コード": "07",
   "レース": "12R",
   "着順": "1-3-2",
   "1着": 1,
   "2着": 3,
   "3着": 2,
   "三連単配当": 2420
  },
  {
   "場コード": "08",
   "レース": "1R",
   "着順": "1-5-3",
   "1着": 1,
   "2着": 5,
   "3着": 3,
   "三連単配当": 8490
  },
  {
   "場コード": "08",
   "レース": "2R",
   "着順": "1-3-4",
   "1着": 1,
   "2着": 3,
   "3着": 4,
   "三連単配当": 2120
  },
  {
   "場コード": "08",
   "レース": "3R",
   "着順": "1-3-2",
   "1着": 1,
   "2着": 3,
   "3着": 2,
   "三連単配当": 790
  },
  {
   "場コード": "08",
   "レース": "4R",
   "着順": "3-5-4",
   "1着": 3,
   "2着": 5,
   "3着": 4,
   "三連単配当": 26560
  },
  {
   "場コード": "08",
   "レース": "5R",
   "着順": "1-3-4",
   "1着": 1,
   "2着": 3,
   "3着": 4,
   "三連単配当": 1220
  },
  {
   "場コード": "08",
   "レース": "6R",
   "着順": "1-4-2",
   "1着": 1,
   "2着": 4,
   "3着": 2,
   "三連単配当": 960
  },
  {
   "場コード": "08",
   "レース": "7R",
   "着順": "1-3-2",
   "1着": 1,
   "2着": 3,
   "3着": 2,
   "三連単配当": 1420
  },
  {
   "場コード": "08",
   "レース": "8R",
   "着順": "1-2-4",
   "1着": 1,
   "2着": 2,
   "3着": 4,
   "三連単配当": 2920
  },
  {
   "場コード": "08",
   "レース": "9R",
   "着順": "4-5-1",
   "1着": 4,
   "2着": 5,
   "3着": 1,
   "三連単配当": 5880
  },
  {
   "場コード": "08",
   "レース": "10R",
   "着順": "2-3-4",
   "1着": 2,
   "2着": 3,
   "3着": 4,
   "三連単配当": 18750
  },
  {
   "場コード": "08",
   "レース": "11R",
   "着順": "1-2-3",
   "1着": 1,
   "2着": 2,
   "3着": 3,
   "三連単配当": 870
  },
  {
   "場コード": "08",
   "レース": "12R",
   "着順": "1-4-3",
   "1着": 1,
   "2着": 4,
   "3着": 3,
   "三連単配当": 2990
  },
  {
   "場コード": "09",
   "レース": "1R",
   "着順": "1-2-4",
   "1着": 1,
   "2着": 2,
   "3着": 4,
   "三連単配当": 490
  },
  {
   "場コード": "09",
   "レース": "2R",
   "着順": "5-1-3",
   "1着": 5,
   "2着": 1,
   "3着": 3,
   "三連単配当": 5780
  },
  {
   "場コード": "09",
   "レース": "3R",
   "着順": "1-5-3",
   "1着": 1,
   "2着": 5,
   "3着": 3,
   "三連単配当": 3430
  },
  {
   "場コード": "09",
   "レース": "4R",
   "着順": "5-1-3",
   "1着": 5,
   "2着": 1,
   "3着": 3,
   "三連単配当": 5820
  },
  {
   "場コード": "09",
   "レース": "5R",
   "着順": "1-3-6",
   "1着": 1,
   "2着": 3,
   "3着": 6,
   "三連単配当": 6090
  },
  {
   "場コード": "09",
   "レース": "6R",
   "着順": "6-4-1",
   "1着": 6,
   "2着": 4,
   "3着": 1,
   "三連単配当": 6650
  },
  {
   "場コード": "09",
   "レース": "7R",
   "着順": "5-2-4",
   "1着": 5,
   "2着": 2,
   "3着": 4,
   "三連単配当": 9820
  },
  {
   "場コード": "09",
   "レース": "8R",
   "着順": "2-3-6",
   "1着": 2,
   "2着": 3,
   "3着": 6,
   "三連単配当": 3450
  },
  {
   "場コード": "09",
   "レース": "9R",
   "着順": "1-2-3",
   "1着": 1,
   "2着": 2,
   "3着": 3,
   "三連単配当": 1720
  },
  {
   "場コード": "09",
   "レース": "10R",
   "着順": "3-2-1",
   "1着": 3,
   "2着": 2,
   "3着": 1,
   "三連単配当": 5610
  },
  {
   "場コード": "09",
   "レース": "11R",
   "着順": "1-3-4",
   "1着": 1,
   "2着": 3,
   "3着": 4,
   "三連単配当": 340
  },
  {
   "場コード": "09",
   "レース": "12R",
   "着順": "4-5-1",
   "1着": 4,
   "2着": 5,
   "3着": 1,
   "三連単配当": 4470
  },
  {
   "場コード": "13",
   "レース": "1R",
   "着順": "3-6-1",
   "1着": 3,
   "2着": 6,
   "3着": 1,
   "三連単配当": 1490
  },
  {
   "場コード": "13",
   "レース": "2R",
   "着順": "1-4-3",
   "1着": 1,
   "2着": 4,
   "3着": 3,
   "三連単配当": 1350
  },
  {
   "場コード": "13",
   "レース": "3R",
   "着順": "5-3-4",
   "1着": 5,
   "2着": 3,
   "3着": 4,
   "三連単配当": 1300
  },
  {
   "場コード": "13",
   "レース": "4R",
   "着順": "1-2-3",
   "1着": 1,
   "2着": 2,
   "3着": 3,
   "三連単配当": 760
  },
  {
   "場コード": "13",
   "レース": "5R",
   "着順": "1-2-4",
   "1着": 1,
   "2着": 2,
   "3着": 4,
   "三連単配当": 3760
  },
  {
   "場コード": "13",
   "レース": "6R",
   "着順": "1-4-6",
   "1着": 1,
   "2着": 4,
   "3着": 6,
   "三連単配当": 1250
  },
  {
   "場コード": "13",
   "レース": "7R",
   "着順": "4-1-2",
   "1着": 4,
   "2着": 1,
   "3着": 2,
   "三連単配当": 1640
  },
  {
   "場コード": "13",
   "レース": "8R",
   "着順": "6-3-2",
   "1着": 6,
   "2着": 3,
   "3着": 2,
   "三連単配当": 62140
  },
  {
   "場コード": "13",
   "レース": "9R",
   "着順": "1-3-6",
   "1着": 1,
   "2着": 3,
   "3着": 6,
   "三連単配当": 2980
  },
  {
   "場コード": "13",
   "レース": "10R",
   "着順": "6-1-4",
   "1着": 6,
   "2着": 1,
   "3着": 4,
   "三連単配当": 7200
  },
  {
   "場コード": "13",
   "レース": "11R",
   "着順": "1-2-4",
   "1着": 1,
   "2着": 2,
   "3着": 4,
   "三連単配当": 2110
  },
  {
   "場コード": "13",
   "レース": "12R",
   "着順": "1-3-4",
   "1着": 1,
   "2着": 3,
   "3着": 4,
   "三連単配当": 2120
  },
  {
   "場コード": "17",
   "レース": "1R",
   "着順": "5-6-2",
   "1着": 5,
   "2着": 6,
   "3着": 2,
   "三連単配当": 40850
  },
  {
   "場コード": "17",
   "レース": "2R",
   "着順": "3-4-6",
   "1着": 3,
   "2着": 4,
   "3着": 6,
   "三連単配当": 1070
  },
  {
   "場コード": "17",
   "レース": "3R",
   "着順": "3-2-5",
   "1着": 3,
   "2着": 2,
   "3着": 5,
   "三連単配当": 2780
  },
  {
   "場コード": "17",
   "レース": "4R",
   "着順": "4-6-2",
   "1着": 4,
   "2着": 6,
   "3着": 2,
   "三連単配当": 2890
  },
  {
   "場コード": "17",
   "レース": "5R",
   "着順": "1-4-3",
   "1着": 1,
   "2着": 4,
   "3着": 3,
   "三連単配当": 1350
  },
  {
   "場コード": "17",
   "レース": "6R",
   "着順": "1-6-2",
   "1着": 1,
   "2着": 6,
   "3着": 2,
   "三連単配当": 10920
  },
  {
   "場コード": "17",
   "レース": "7R",
   "着順": "1-2-4",
   "1着": 1,
   "2着": 2,
   "3着": 4,
   "三連単配当": 3190
  },
  {
   "場コード": "17",
   "レース": "8R",
   "着順": "1-3-5",
   "1着": 1,
   "2着": 3,
   "3着": 5,
   "三連単配当": 8160
  },
  {
   "場コード": "17",
   "レース": "9R",
   "着順": "1-5-4",
   "1着": 1,
   "2着": 5,
   "3着": 4,
   "三連単配当": 3450
  },
  {
   "場コード": "17",
   "レース": "10R",
   "着順": "1-4-6",
   "1着": 1,
   "2着": 4,
   "3着": 6,
   "三連単配当": 7090
  },
  {
   "場コード": "17",
   "レース": "11R",
   "着順": "1-3-4",
   "1着": 1,
   "2着": 3,
   "3着": 4,
   "三連単配当": 700
  },
  {
   "場コード": "17",
   "レース": "12R",
   "着順": "5-1-2",
   "1着": 5,
   "2着": 1,
   "3着": 2,
   "三連単配当": 11340
  },
  {
   "場コード": "18",
   "レース": "1R",
   "着順": "1-3-2",
   "1着": 1,
   "2着": 3,
   "3着": 2,
   "三連単配当": 540
  },
  {
   "場コード": "18",
   "レース": "2R",
   "着順": "1-3-4",
   "1着": 1,
   "2着": 3,
   "3着": 4,
   "三連単配当": 840
  },
  {
   "場コード": "18",
   "レース": "3R",
   "着順": "1-3-2",
   "1着": 1,
   "2着": 3,
   "3着": 2,
   "三連単配当": 640
  },
  {
   "場コード": "18",
   "レース": "4R",
   "着順": "2-4-1",
   "1着": 2,
   "2着": 4,
   "3着": 1,
   "三連単配当": 12150
  },
  {
   "場コード": "18",
   "レース": "5R",
   "着順": "2-6-4",
   "1着": 2,
   "2着": 6,
   "3着": 4,
   "三連単配当": 3200
  },
  {
   "場コード": "18",
   "レース": "6R",
   "着順": "2-1-5",
   "1着": 2,
   "2着": 1,
   "3着": 5,
   "三連単配当": 7420
  },
  {
   "場コード": "18",
   "レース": "7R",
   "着順": "4-6-2",
   "1着": 4,
   "2着": 6,
   "3着": 2,
   "三連単配当": 9410
  },
  {
   "場コード": "18",
   "レース": "8R",
   "着順": "1-5-3",
   "1着": 1,
   "2着": 5,
   "3着": 3,
   "三連単配当": 15890
  },
  {
   "場コード": "18",
   "レース": "9R",
   "着順": "2-4-5",
   "1着": 2,
   "2着": 4,
   "3着": 5,
   "三連単配当": 10490
  },
  {
   "場コード": "18",
   "レース": "10R",
   "着順": "5-2-1",
   "1着": 5,
   "2着": 2,
   "3着": 1,
   "三連単配当": 10490
  },
  {
   "場コード": "18",
   "レース": "11R",
   "着順": "1-2-4",
   "1着": 1,
   "2着": 2,
   "3着": 4,
   "三連単配当": 2450
  },
  {
   "場コード": "18",
   "レース": "12R",
   "着順": "1-3-2",
   "1着": 1,
   "2着": 3,
   "3着": 2,
   "三連単配当": 1140
  },
  {
   "場コード": "20",
   "レース": "1R",
   "着順": "1-4-2",
   "1着": 1,
   "2着": 4,
   "3着": 2,
   "三連単配当": 880
  },
  {
   "場コード": "20",
   "レース": "2R",
   "着順": "1-4-2",
   "1着": 1,
   "2着": 4,
   "3着": 2,
   "三連単配当": 4380
  },
  {
   "場コード": "20",
   "レース": "3R",
   "着順": "1-4-3",
   "1着": 1,
   "2着": 4,
   "3着": 3,
   "三連単配当": 12000
  },
  {
   "場コード": "20",
   "レース": "4R",
   "着順": "4-1-3",
   "1着": 4,
   "2着": 1,
   "3着": 3,
   "三連単配当": 30620
  },
  {
   "場コード": "20",
   "レース": "5R",
   "着順": "1-2-4",
   "1着": 1,
   "2着": 2,
   "3着": 4,
   "三連単配当": 350
  },
  {
   "場コード": "20",
   "レース": "6R",
   "着順": "3-4-1",
   "1着": 3,
   "2着": 4,
   "3着": 1,
   "三連単配当": 9380
  },
  {
   "場コード": "20",
   "レース": "7R",
   "着順": "1-4-3",
   "1着": 1,
   "2着": 4,
   "3着": 3,
   "三連単配当": 550
  },
  {
   "場コード": "20",
   "レース": "8R",
   "着順": "1-3-2",
   "1着": 1,
   "2着": 3,
   "3着": 2,
   "三連単配当": 350
  },
  {
   "場コード": "20",
   "レース": "9R",
   "着順": "1-2-4",
   "1着": 1,
   "2着": 2,
   "3着": 4,
   "三連単配当": 800
  },
  {
   "場コード": "20",
   "レース": "10R",
   "着順": "1-3-2",
   "1着": 1,
   "2着": 3,
   "3着": 2,
   "三連単配当": 1450
  },
  {
   "場コード": "20",
   "レース": "11R",
   "着順": "1-3-2",
   "1着": 1,
   "2着": 3,
   "3着": 2,
   "三連単配当": 1080
  },
  {
   "場コード": "20",
   "レース": "12R",
   "着順": "1-2-3",
   "1着": 1,
   "2着": 2,
   "3着": 3,
   "三連単配当": 650
  },
  {
   "場コード": "21",
   "レース": "1R",
   "着順": "1-4-6",
   "1着": 1,
   "2着": 4,
   "3着": 6,
   "三連単配当": 3480
  },
  {
   "場コード": "21",
   "レース": "2R",
   "着順": "1-3-5",
   "1着": 1,
   "2着": 3,
   "3着": 5,
   "三連単配当": 1770
  },
  {
   "場コード": "21",
   "レース": "3R",
   "着順": "1-3-2",
   "1着": 1,
   "2着": 3,
   "3着": 2,
   "三連単配当": 600
  },
  {
   "場コード": "21",
   "レース": "4R",
   "着順": "1-4-3",
   "1着": 1,
   "2着": 4,
   "3着": 3,
   "三連単配当": 910
  },
  {
   "場コード": "21",
   "レース": "5R",
   "着順": "1-5-2",
   "1着": 1,
   "2着": 5,
   "3着": 2,
   "三連単配当": 1280
  },
  {
   "場コード": "21",
   "レース": "6R",
   "着順": "3-1-6",
   "1着": 3,
   "2着": 1,
   "3着": 6,
   "三連単配当": 6240
  },
  {
   "場コード": "21",
   "レース": "7R",
   "着順": "3-1-5",
   "1着": 3,
   "2着": 1,
   "3着": 5,
   "三連単配当": 8650
  },
  {
   "場コード": "21",
   "レース": "8R",
   "着順": "1-2-3",
   "1着": 1,
   "2着": 2,
   "3着": 3,
   "三連単配当": 1000
  },
  {
   "場コード": "21",
   "レース": "9R",
   "着順": "1-4-3",
   "1着": 1,
   "2着": 4,
   "3着": 3,
   "三連単配当": 11290
  },
  {
   "場コード": "21",
   "レース": "10R",
   "着順": "1-2-5",
   "1着": 1,
   "2着": 2,
   "3着": 5,
   "三連単配当": 1300
  },
  {
   "場コード": "21",
   "レース": "11R",
   "着順": "1-2-5",
   "1着": 1,
   "2着": 2,
   "3着": 5,
   "三連単配当": 1940
  },
  {
   "場コード": "21",
   "レース": "12R",
   "着順": "3-4-6",
   "1着": 3,
   "2着": 4,
   "3着": 6,
   "三連単配当": 9190
  },
  {
   "場コード": "24",
   "レース": "1R",
   "着順": "5-1-6",
   "1着": 5,
   "2着": 1,
   "3着": 6,
   "三連単配当": 9140
  },
  {
   "場コード": "24",
   "レース": "2R",
   "着順": "1-4-5",
   "1着": 1,
   "2着": 4,
   "3着": 5,
   "三連単配当": 2370
  },
  {
   "場コード": "24",
   "レース": "3R",
   "着順": "1-3-2",
   "1着": 1,
   "2着": 3,
   "3着": 2,
   "三連単配当": 1080
  },
  {
   "場コード": "24",
   "レース": "4R",
   "着順": "3-1-6",
   "1着": 3,
   "2着": 1,
   "3着": 6,
   "三連単配当": 5550
  },
  {
   "場コード": "24",
   "レース": "5R",
   "着順": "1-5-2",
   "1着": 1,
   "2着": 5,
   "3着": 2,
   "三連単配当": 2450
  },
  {
   "場コード": "24",
   "レース": "6R",
   "着順": "6-1-3",
   "1着": 6,
   "2着": 1,
   "3着": 3,
   "三連単配当": 6110
  },
  {
   "場コード": "24",
   "レース": "7R",
   "着順": "1-4-2",
   "1着": 1,
   "2着": 4,
   "3着": 2,
   "三連単配当": 1710
  },
  {
   "場コード": "24",
   "レース": "8R",
   "着順": "1-2-6",
   "1着": 1,
   "2着": 2,
   "3着": 6,
   "三連単配当": 7100
  },
  {
   "場コード": "24",
   "レース": "9R",
   "着順": "1-2-6",
   "1着": 1,
   "2着": 2,
   "3着": 6,
   "三連単配当": 2090
  },
  {
   "場コード": "24",
   "レース": "10R",
   "着順": "1-3-2",
   "1着": 1,
   "2着": 3,
   "3着": 2,
   "三連単配当": 1250
  },
  {
   "場コード": "24",
   "レース": "11R",
   "着順": "1-3-5",
   "1着": 1,
   "2着": 3,
   "3着": 5,
   "三連単配当": 930
  },
  {
   "場コード": "24",
   "レース": "12R",
   "着順": "3-1-5",
   "1着": 3,
   "2着": 1,
   "3着": 5,
   "三連単配当": 3220
  }
 ]
}